csfutils/__init__.py
csfutils/_blob_arg.py
csfutils/_client.py
csfutils/_const.py
csfutils/_utils.py
csfutils/blob/__init__.py
csfutils/blob/_access_token.py
csfutils/blob/_path.py
csfutils/blob/_upload.py
csfutils/url_type.py
csfutils-0.2.0.dist-info/LICENSE
csfutils-0.2.0.dist-info/WHEEL
csfutils-0.2.0.dist-info/METADATA
csfutils-0.2.0.dist-info/RECORD
