Metadata-Version: 2.1
Name: csfutils
Version: 0.2.0
Summary: Python utility for Cloud Storage for Firebase.
Home-page: https://github.com/quwac/cloud-storage-for-firebase-utils
License: MIT
Keywords: Firebase,Google Cloud Storage
Author: quwac
Author-email: 53551867+quwac@users.noreply.github.com
Requires-Python: >=3.6,<4.0
Classifier: License :: OSI Approved :: MIT License
Classifier: Programming Language :: Python :: 3
Classifier: Programming Language :: Python :: 3.6
Classifier: Programming Language :: Python :: 3.7
Classifier: Programming Language :: Python :: 3.8
Classifier: Programming Language :: Python :: 3.9
Requires-Dist: google-cloud-storage (>=1.35.0,<2.0.0)
Project-URL: Repository, https://github.com/quwac/cloud-storage-for-firebase-utils
